Workbook

Sheet Read me
A1: Reven / Partner Revenue OS — Top-Quartile Growth Model
A2: Companion to the three strategy docs (Growth Archetype + Deep-Research + Rationale Annex). A live, formula-driven model.
A4: HOW TO USE — 3 steps
A5: 1. Go to the 'Assumptions' tab and replace every YELLOW cell with your own numbers. Everything else recomputes automatically.
A6: 2. Read the 'Dashboard' tab: ARR, the cohort-driven NRR, and every top-quartile efficiency metric vs its benchmark line.
A7: 3. Use 'ARR & Cohorts' to see the J-curve per acquisition cohort (the engine behind NRR). 'Benchmarks' lists the verified lines + sources.
A9: COLOUR LEGEND
A10: YELLOW = an input you edit. WHITE = a computed cell (do not overwrite). GREEN = a pass/read flag.
A12: WHAT THIS MODEL ENCODES (the strategy, made numeric)
A13: • NRR is built bottom-up from COHORTS, with net retention rising by cohort age then plateauing — i.e. the module-ladder J-curve. Raising the
A14: 'net retention by cohort age' inputs is exactly the 'reprice to value + climb the ladder' lever (Pillars 1 & 3). It is the dial for 110% -> 120%+.
A15: • The illustrative inputs land ~$2.0M (Y2) -> ~$5.3M (Y3, inside your KSA SOM) -> ~$13.9M -> ~$33.6M -> ~$72.6M (Y6): a capital-efficient
... A21: External benchmark lines on the 'Benchmarks' tab are directional (knowledge cutoff Jan-2026, fetch-blocked research) — re-verify before investor use.

Sheet Assumptions
A1: ASSUMPTIONS — edit the YELLOW cells only
A2: (values shown are ILLUSTRATIVE placeholders — replace with your own)
A4: Driver | B4: Y1 | C4: Y2 | D4: Y3 | E4: Y4 | F4: Y5 | G4: Y6 | I4: Note / rationale
A5: New-logo ARR added ($) [gross new bookings] | B5: 500000 | C5: 1500000 | D5: 3000000 | E5: 8000000 | F5: 18000000 | G5: 35000000 | I5: Y1-3 ~ KSA SOM; Y4-6 step-up = GCC + flow + global. The new-logo engine.
A7: Net revenue retention by COHORT AGE (the NRR / ladder engine)
A8: Cohort age (years since acquired) | B8: 1 | C8: 2 | D8: 3 | E8: 4 | F8: 5 | G8: — | I8: Age, not calendar year.
A9: Net retention applied at this age (x) | B9: 1.1 | C9: 1.15 | D9: 1.16 | E9: 1.1 | F9: 1.06 | G9: — | I9: >1.00 = net expansion (incl. churn). Climbs then plateaus = the cohort J-curve. RAISE THESE to model 120%+ NRR.
A11: Gross margin % (software-grade; fence flow!) | B11: 0.65 | C11: 0.68 | D11: 0.7 | E11: 0.72 | F11: 0.74 | G11: 0.75 | I11: >=70% floor. If flow is booked gross, report it separately or this falls (Toast -> 25% blended).
A12: S&M spend ($) per year | B12: 800000 | C12: 1800000 | D12: 3500000 | E12: 7000000 | F12: 13000000 | G12: 22000000 | I12: Drives magic number & CAC payback. Hold founder-led until rep #1 ramps.
A13: Net cash burned ($) per year [positive] | B13: 1500000 | C13: 2500000 | D13: 3500000 | E13: 5000000 | F13: 6000000 | G13: 4000000 | I13: Drives burn multiple. Your SAR cost base is the edge here.
A14: FCF margin % (for Rule of 40; negative early) | B14: -2 | C14: -1.2 | D14: -0.6 | E14: -0.25 | F14: -0.05 | G14: 0.1 | I14: Rule-of-40 is a scale-phase metric; shown for the later years.

Sheet ARR & Cohorts
A1: ARR & COHORT WATERFALL — the J-curve per acquisition cohort (all computed)
A2: Each cohort starts at its new-logo ARR, then ages by the 'net retention by age' curve from Assumptions.
A4: Cohort \ Year | B4: Y1 | C4: Y2 | D4: Y3 | E4: Y4 | F4: Y5 | G4: Y6
A5: Cohort Y1 | B5: =Assumptions!B5 | C5: =B5*Assumptions!B9 | D5: =C5*Assumptions!C9 | E5: =D5*Assumptions!D9 | F5: =E5*Assumptions!E9 | G5: =F5*Assumptions!F9
A6: Cohort Y2 | C6: =Assumptions!C5 | D6: =C6*Assumptions!B9 | E6: =D6*Assumptions!C9 | F6: =E6*Assumptions!D9 | G6: =F6*Assumptions!E9
A7: Cohort Y3 | D7: =Assumptions!D5 | E7: =D7*Assumptions!B9 | F7: =E7*Assumptions!C9 | G7: =F7*Assumptions!D9
A8: Cohort Y4 | E8: =Assumptions!E5 | F8: =E8*Assumptions!B9 | G8: =F8*Assumptions!C9
A9: Cohort Y5 | F9: =Assumptions!F5 | G9: =F9*Assumptions!B9
A10: Cohort Y6 | G10: =Assumptions!G5
A11: TOTAL ARR ($) | B11: =SUM(B5:B10) | C11: =SUM(C5:C10) | D11: =SUM(D5:D10) | E11: =SUM(E5:E10) | F11: =SUM(F5:F10) | G11: =SUM(G5:G10)
A12: Blended NRR (prior book) | B12: n/a | C12: =IFERROR((C11-Assumptions!C5)/B11,"") | D12: =IFERROR((D11-Assumptions!D5)/C11,"") | E12: =IFERROR((E11-Assumptions!E5)/D11,"") | F12: =IFERROR((F11-Assumptions!F5)/E11,"") | G12: =IFERROR((G11-Assumptions!G5)/F11,"")

Sheet Dashboard
A1: DASHBOARD — growth, retention & top-quartile efficiency (all computed)
A3: Metric | B3: Y1 | C3: Y2 | D3: Y3 | E3: Y4 | F3: Y5 | G3: Y6 | H3: Top-quartile line | I3: Latest-year read
A4: ARR ($) | B4: ='ARR & Cohorts'!B11 | C4: ='ARR & Cohorts'!C11 | D4: ='ARR & Cohorts'!D11 | E4: ='ARR & Cohorts'!E11 | F4: ='ARR & Cohorts'!F11 | G4: ='ARR & Cohorts'!G11 | H4: — (scale, not a ratio)
A5: New-logo ARR ($) | B5: =Assumptions!B5 | C5: =Assumptions!C5 | D5: =Assumptions!D5 | E5: =Assumptions!E5 | F5: =Assumptions!F5 | G5: =Assumptions!G5 | H5: —
A6: Net new ARR ($) | B6: =B4 | C6: =C4-B4 | D6: =D4-C4 | E6: =E4-D4 | F6: =F4-E4 | G6: =G4-F4 | H6: —
A7: YoY ARR growth % | B7: n/a | C7: =IFERROR(C4/B4-1,"") | D7: =IFERROR(D4/C4-1,"") | E7: =IFERROR(E4/D4-1,"") | F7: =IFERROR(F4/E4-1,"") | G7: =IFERROR(G4/F4-1,"") | H7: >=3x (triple) early; >= Mendoza floor | I7: =IF(G7>=2,"3x+",IF(G7>=1,"2x+","check"))
A8: Growth persistence (x) | B8: n/a | C8: n/a | D8: =IFERROR(D7/C7,"") | E8: =IFERROR(E7/D7,"") | F8: =IFERROR(F7/E7,"") | G8: =IFERROR(G7/F7,"") | H8: plan ~0.75 (Bessemer); 0.85 = Scale VP best
A9: Blended NRR % | B9: n/a | C9: ='ARR & Cohorts'!C12 | D9: ='ARR & Cohorts'!D12 | E9: ='ARR & Cohorts'!E12 | F9: ='ARR & Cohorts'!F12 | G9: ='ARR & Cohorts'!G12 | H9: >=120% top-Q (compliance-SoR band ~110%) | I9: =IF(G9>=1.2,"top-Q",IF(G9>=1.1,"SoR band","build ladder"))
A10: Gross margin % | B10: =Assumptions!B11 | C10: =Assumptions!C11 | D10: =Assumptions!D11 | E10: =Assumptions!E11 | F10: =Assumptions!F11 | G10: =Assumptions!G11 | H10: >=70% (software multiple) | I10: =IF(G10>=0.7,"software-grade","flow diluting")
A11: Burn multiple (x) | B11: =IFERROR(Assumptions!B13/B6,"") | C11: =IFERROR(Assumptions!C13/C6,"") | D11: =IFERROR(Assumptions!D13/D6,"") | E11: =IFERROR(Assumptions!E13/E6,"") | F11: =IFERROR(Assumptions!F13/F6,"") | G11: =IFERROR(Assumptions!G13/G6,"") | H11: <1 amazing | 1-1.5 great | 1.5-2 good | I11: =IF(G11<1,"amazing",IF(G11<1.5,"great",IF(G11<2,"good","improve")))
A12: Magic number (x) | B12: n/a | C12: =IFERROR(C6/Assumptions!B12,"") | D12: =IFERROR(D6/Assumptions!C12,"") | E12: =IFERROR(E6/Assumptions!D12,"") | F12: =IFERROR(F6/Assumptions!E12,"") | G12: =IFERROR(G6/Assumptions!F12,"") | H12: >0.75 good | >1.0 great | I12: =IF(G12>1,"great",IF(G12>0.75,"good","hold scaling"))
A13: CAC payback (months) | B13: n/a | C13: =IFERROR(12*Assumptions!B12/(C6*C10),"") | D13: =IFERROR(12*Assumptions!C12/(D6*D10),"") | E13: =IFERROR(12*Assumptions!D12/(E6*E10),"") | F13: =IFERROR(12*Assumptions!E12/(F6*F10),"") | G13: =IFERROR(12*Assumptions!F12/(G6*G10),"") | H13: <16 enterprise top-Q (don't chase <12) | I13: =IF(G13<16,"top-Q",IF(G13<24,"ok","slow"))
A14: Rule of 40 (growth%+FCF%) | B14: n/a | C14: =IFERROR(C7+Assumptions!C14,"") | D14: =IFERROR(D7+Assumptions!D14,"") | E14: =IFERROR(E7+Assumptions!E14,"") | F14: =IFERROR(F7+Assumptions!F14,"") | G14: =IFERROR(G7+Assumptions!G14,"") | H14: >=40% (scale phase) | I14: =IF(G14>=0.4,"clears 40","scale-phase")
A16: T2D3 reference ($2M start at Y2) | C16: 2000000 | D16: 6000000 | E16: 18000000 | F16: 36000000 | G16: 72000000 | H16: Triple,Triple,Double,Double from $2M
A17: Read: the illustrative plan reaches ~T2D3's Y6 destination via efficient DOUBLES (D5-plus), not triples — same end, less dilution.

Sheet Benchmarks
A1: VERIFIED TOP-QUARTILE BENCHMARKS (directional; re-verify before investor use)
A3: Metric | B3: Median | C3: Top quartile / target | D3: Confidence | E3: Source (knowledge cutoff Jan-2026)
A4: NRR | B4: ~101% | C4: 110-118% broad / 120-130% ent. | D4: HIGH | E4: KeyBanc'24, ICONIQ'25, SaaS Capital'25, High Alpha'25
A5: Compliance-SoR NRR | B5: — | C5: ~108-118% (the realistic band) | D5: HIGH | E5: Avalara 116%, Vertex 109%
A6: GRR | B6: ~88-92% | C6: >=92% (SoR 95-98%) | D6: HIGH | E6: ICONIQ'24; Workday >95%, ServiceNow 98%
A7: CAC payback | B7: ~18-20 mo | C7: <16 mo (enterprise top-Q) | D7: HIGH | E7: ICONIQ'25; High Alpha'25
A8: Burn multiple | B8: ~1.5-2x | C8: <1.5x; ~1.0x elite | D8: HIGH | E8: Sacks (Craft): <1 amazing/1-1.5 great/1.5-2 good
A9: Magic number | B9: ~0.90 | C9: >0.75 good; >1.0 great | D9: HIGH | E9: Scale VP; High Alpha'25
A10: Rule of 40 | B10: ~28-34% pass | C10: >=40 (top-Q across ARR bands) | D10: HIGH | E10: KeyBanc; High Alpha'25 (majority now fail)
A11: Growth persistence | B11: — | C11: ~0.85 (Scale VP) / 0.70-0.80 (Bessemer) | D11: HIGH | E11: O'Driscoll Scale VP; Bessemer endurance
A12: Mendoza line (IPO) | B12: — | C12: path to ~$250M ARR, >=25% growth | D12: HIGH | E12: Scale VP 2024 update (was $100M, 2018)
A13: Premature scaling | B13: — | C13: ~74% of startups fail from it | D13: HIGH | E13: Startup Genome (n>3,200)
A14: Avalara exit | B14: — | C14: $8.4B / 27% premium @ ~116% NRR, 40% gr. | D14: HIGH | E14: Vista take-private, Aug-Oct 2022
... A19: Foodics (KSA lighthouse) | B19: — | C19: $170M Series C (Prosus+Sanabil/PIF) | D19: HIGH | E19: Apr 2022; vertical SaaS->payments->lending
